{
  "warnings": [
    {
      "message": "There were 205 words in the input. We need a minimum of 600, preferably 1,200 or more, to compute statistically significant estimates", 
      "warning_id": "WORD_COUNT_MESSAGE"
    }
  ], 
  "tree": {
    "children": [
      {
        "children": [
          {
            "category": "personality", 
            "percentage": 0.9349279773632903, 
            "children": [
              {
                "category": "personality", 
                "name": "Openness", 
                "sampling_error": 0.0643209985, 
                "id": "Openness", 
                "percentage": 0.9349279773632903, 
                "children": [
                  {
                    "category": "personality", 
                    "percentage": 0.3150769307332758, 
                    "id": "Adventurousness", 
                    "sampling_error": 0.053718790499999995, 
                    "name": "Adventurousness"
                  }, 
                  {
                    "category": "personality", 
                    "percentage": 0.565886491049537, 
                    "id": "Artistic interests", 
                    "sampling_error": 0.1094597725, 
                    "name": "Artistic interests"
                  }, 
                  {
                    "category": "personality", 
                    "percentage": 0.4454789485309786, 
                    "id": "Emotionality", 
                    "sampling_error": 0.050226637000000005, 
                    "name": "Emotionality"
                  }, 
                  {
                    "category": "personality", 
                    "percentage": 0.61970497938539, 
                    "id": "Imagination", 
                    "sampling_error": 0.0678514405, 
                    "name": "Imagination"
                  }, 
                  {
                    "category": "personality", 
                    "percentage": 0.7486236627809024, 
                    "id": "Intellect", 
                    "sampling_error": 0.0595329415, 
                    "name": "Intellect"
                  }, 
                  {
                    "category": "personality", 
                    "percentage": 0.8481654616995505, 
                    "id": "Liberalism", 
                    "sampling_error": 0.0875862605, 
                    "name": "Authority-challenging"
                  }
                ]
              }, 
              {
                "category": "personality", 
                "name": "Conscientiousness", 
                "sampling_error": 0.08034924900000001, 
                "id": "Conscientiousness", 
                "percentage": 0.2545526889255297, 
                "children": [
                  {
                    "category": "personality", 
                    "percentage": 0.21929229498626768, 
                    "id": "Achievement striving", 
                    "sampling_error": 0.103574211, 
                    "name": "Achievement striving"
                  }, 
                  {
                    "category": "personality", 
                    "percentage": 0.43463611114403616, 
                    "id": "Cautiousness", 
                    "sampling_error": 0.09591269699999999, 
                    "name": "Cautiousness"
                  }, 
                  {
                    "category": "personality", 
                    "percentage": 0.13023957091107125, 
                    "id": "Dutifulness", 
                    "sampling_error": 0.064464714, 
                    "name": "Dutifulness"
                  }, 
                  {
                    "category": "personality", 
                    "percentage": 0.9436297508919065, 
                    "id": "Orderliness", 
                    "sampling_error": 0.0736915625, 
                    "name": "Orderliness"
                  }, 
                  {
                    "category": "personality", 
                    "percentage": 0.19292323034456327, 
                    "id": "Self-discipline", 
                    "sampling_error": 0.049232859, 
                    "name": "Self-discipline"
                  }, 
                  {
                    "category": "personality", 
                    "percentage": 0.11439988254061528, 
                    "id": "Self-efficacy", 
                    "sampling_error": 0.096863438, 
                    "name": "Self-efficacy"
                  }
                ]
              }, 
              {
                "category": "personality", 
                "name": "Extraversion", 
                "sampling_error": 0.0600822535, 
                "id": "Extraversion", 
                "percentage": 0.48328843656104076, 
                "children": [
                  {
                    "category": "personality", 
                    "percentage": 0.3210402558198308, 
                    "id": "Activity level", 
                    "sampling_error": 0.08218142049999999, 
                    "name": "Activity level"
                  }, 
                  {
                    "category": "personality", 
                    "percentage": 0.12172782785428904, 
                    "id": "Assertiveness", 
                    "sampling_error": 0.0874930595, 
                    "name": "Assertiveness"
                  }, 
                  {
                    "category": "personality", 
                    "percentage": 0.19192907323957314, 
                    "id": "Cheerfulness", 
                    "sampling_error": 0.1101098195, 
                    "name": "Cheerfulness"
                  }, 
                  {
                    "category": "personality", 
                    "percentage": 0.20806478043059173, 
                    "id": "Excitement-seeking", 
                    "sampling_error": 0.084044748, 
                    "name": "Excitement-seeking"
                  }, 
                  {
                    "category": "personality", 
                    "percentage": 0.2672220341426966, 
                    "id": "Friendliness", 
                    "sampling_error": 0.079078227, 
                    "name": "Outgoing"
                  }, 
                  {
                    "category": "personality", 
                    "percentage": 0.34726269362349926, 
                    "id": "Gregariousness", 
                    "sampling_error": 0.060310401, 
                    "name": "Gregariousness"
                  }
                ]
              }, 
              {
                "category": "personality", 
                "name": "Agreeableness", 
                "sampling_error": 0.101034785, 
                "id": "Agreeableness", 
                "percentage": 0.29099314274034616, 
                "children": [
                  {
                    "category": "personality", 
                    "percentage": 0.3611687982639355, 
                    "id": "Altruism", 
                    "sampling_error": 0.074516547, 
                    "name": "Altruism"
                  }, 
                  {
                    "category": "personality", 
                    "percentage": 0.3063655335328556, 
                    "id": "Cooperation", 
                    "sampling_error": 0.0832709355, 
                    "name": "Cooperation"
                  }, 
                  {
                    "category": "personality", 
                    "percentage": 0.5882564061413733, 
                    "id": "Modesty", 
                    "sampling_error": 0.0593868095, 
                    "name": "Modesty"
                  }, 
                  {
                    "category": "personality", 
                    "percentage": 0.32735870792750354, 
                    "id": "Morality", 
                    "sampling_error": 0.0662152615, 
                    "name": "Uncompromising"
                  }, 
                  {
                    "category": "personality", 
                    "percentage": 0.6012145700399865, 
                    "id": "Sympathy", 
                    "sampling_error": 0.102208299, 
                    "name": "Sympathy"
                  }, 
                  {
                    "category": "personality", 
                    "percentage": 0.11187433272318459, 
                    "id": "Trust", 
                    "sampling_error": 0.060064646, 
                    "name": "Trust"
                  }
                ]
              }, 
              {
                "category": "personality", 
                "name": "Emotional range", 
                "sampling_error": 0.095468815, 
                "id": "Neuroticism", 
                "percentage": 0.8150253429702952, 
                "children": [
                  {
                    "category": "personality", 
                    "percentage": 0.6214014743140317, 
                    "id": "Anger", 
                    "sampling_error": 0.0983521135, 
                    "name": "Fiery"
                  }, 
                  {
                    "category": "personality", 
                    "percentage": 0.7420843238575314, 
                    "id": "Anxiety", 
                    "sampling_error": 0.058145276499999995, 
                    "name": "Prone to worry"
                  }, 
                  {
                    "category": "personality", 
                    "percentage": 0.8174626975946215, 
                    "id": "Depression", 
                    "sampling_error": 0.062316331999999995, 
                    "name": "Melancholy"
                  }, 
                  {
                    "category": "personality", 
                    "percentage": 0.47134319665518665, 
                    "id": "Immoderation", 
                    "sampling_error": 0.0558878605, 
                    "name": "Immoderation"
                  }, 
                  {
                    "category": "personality", 
                    "percentage": 0.7381711245362268, 
                    "id": "Self-consciousness", 
                    "sampling_error": 0.060274056500000006, 
                    "name": "Self-consciousness"
                  }, 
                  {
                    "category": "personality", 
                    "percentage": 0.7315600749367539, 
                    "id": "Vulnerability", 
                    "sampling_error": 0.089887073, 
                    "name": "Susceptible to stress"
                  }
                ]
              }
            ], 
            "id": "Openness_parent", 
            "name": "Openness"
          }
        ], 
        "id": "personality", 
        "name": "Big 5"
      }, 
      {
        "children": [
          {
            "category": "needs", 
            "percentage": 0.10895455952003602, 
            "children": [
              {
                "category": "needs", 
                "percentage": 0.2055746551090813, 
                "id": "Challenge", 
                "sampling_error": 0.08683700899999999, 
                "name": "Challenge"
              }, 
              {
                "category": "needs", 
                "percentage": 0.23586779644201156, 
                "id": "Closeness", 
                "sampling_error": 0.085718171, 
                "name": "Closeness"
              }, 
              {
                "category": "needs", 
                "percentage": 0.5660908301515353, 
                "id": "Curiosity", 
                "sampling_error": 0.1241117515, 
                "name": "Curiosity"
              }, 
              {
                "category": "needs", 
                "percentage": 0.3515010732266031, 
                "id": "Excitement", 
                "sampling_error": 0.113284289, 
                "name": "Excitement"
              }, 
              {
                "category": "needs", 
                "percentage": 0.22087413804280187, 
                "id": "Harmony", 
                "sampling_error": 0.113455748, 
                "name": "Harmony"
              }, 
              {
                "category": "needs", 
                "percentage": 0.25630248159444147, 
                "id": "Ideal", 
                "sampling_error": 0.1028889125, 
                "name": "Ideal"
              }, 
              {
                "category": "needs", 
                "percentage": 0.16019550967370266, 
                "id": "Liberty", 
                "sampling_error": 0.1499116815, 
                "name": "Liberty"
              }, 
              {
                "category": "needs", 
                "percentage": 0.2821051925500886, 
                "id": "Love", 
                "sampling_error": 0.104416364, 
                "name": "Love"
              }, 
              {
                "category": "needs", 
                "percentage": 0.588259622604078, 
                "id": "Practicality", 
                "sampling_error": 0.09068285599999999, 
                "name": "Practicality"
              }, 
              {
                "category": "needs", 
                "percentage": 0.30347489005888306, 
                "id": "Self-expression", 
                "sampling_error": 0.084416453, 
                "name": "Self-expression"
              }, 
              {
                "category": "needs", 
                "percentage": 0.19276336182272813, 
                "id": "Stability", 
                "sampling_error": 0.110340857, 
                "name": "Stability"
              }, 
              {
                "category": "needs", 
                "percentage": 0.10895455952003602, 
                "id": "Structure", 
                "sampling_error": 0.08288348150000001, 
                "name": "Structure"
              }
            ], 
            "id": "Structure_parent", 
            "name": "Structure"
          }
        ], 
        "id": "needs", 
        "name": "Needs"
      }, 
      {
        "children": [
          {
            "category": "values", 
            "percentage": 0.21197631694335023, 
            "children": [
              {
                "category": "values", 
                "percentage": 0.21197631694335023, 
                "id": "Conservation", 
                "sampling_error": 0.070450292, 
                "name": "Conservation"
              }, 
              {
                "category": "values", 
                "percentage": 0.4690373201392996, 
                "id": "Openness to change", 
                "sampling_error": 0.0674449575, 
                "name": "Openness to change"
              }, 
              {
                "category": "values", 
                "percentage": 0.47750808620508184, 
                "id": "Hedonism", 
                "sampling_error": 0.14186923099999998, 
                "name": "Hedonism"
              }, 
              {
                "category": "values", 
                "percentage": 0.3529525262731484, 
                "id": "Self-enhancement", 
                "sampling_error": 0.1075125425, 
                "name": "Self-enhancement"
              }, 
              {
                "category": "values", 
                "percentage": 0.2713422388266449, 
                "id": "Self-transcendence", 
                "sampling_error": 0.0854465525, 
                "name": "Self-transcendence"
              }
            ], 
            "id": "Conservation_parent", 
            "name": "Conservation"
          }
        ], 
        "id": "values", 
        "name": "Values"
      }
    ], 
    "id": "r", 
    "name": "root"
  }, 
  "word_count": 205, 
  "processed_lang": "en", 
  "source": "*UNKNOWN*", 
  "word_count_message": "There were 205 words in the input. We need a minimum of 600, preferably 1,200 or more, to compute statistically significant estimates", 
  "id": "*UNKNOWN*"
}